lintr/__init__.py
lintr/__main__.py
lintr/cli.py
lintr/config.py
lintr/gh.py
lintr/linter.py
lintr/rule_manager.py
lintr/util.py
lintr/rules/__init__.py
lintr/rules/base.py
lintr/rules/branch_rules.py
lintr/rules/context.py
lintr/rules/default_ruleset.py
lintr/rules/empty_ruleset.py
lintr/rules/general.py
lintr/rules/gitflow.py
lintr/rules/permission_rules.py
lintr/templates/default_config.yml
lintr-0.2.0.dist-info/METADATA
lintr-0.2.0.dist-info/WHEEL
lintr-0.2.0.dist-info/entry_points.txt
lintr-0.2.0.dist-info/RECORD
