Metadata-Version: 2.4
Name: lintr
Version: 0.2.0
Summary: A Python-based command-line application to lint and enforce consistent settings across GitHub repositories
Author-email: Jens Keiner <jens.keiner@gmail.com>
License: MIT
Classifier: Development Status :: 3 - Alpha
Classifier: Environment :: Console
Classifier: Intended Audience :: Developers
Classifier: License :: OSI Approved :: MIT License
Classifier: Operating System :: OS Independent
Classifier: Programming Language :: Python :: 3
Classifier: Programming Language :: Python :: 3.12
Classifier: Topic :: Software Development :: Quality Assurance
Requires-Python: >=3.12
Requires-Dist: colorama>=0.4.6
Requires-Dist: pydantic-settings>=2.1.0
Requires-Dist: pydantic>=2.5.3
Requires-Dist: pygithub
Requires-Dist: pyyaml>=6.0.1
Requires-Dist: pyyaml>=6.0.2
